pyprediktormapclient/__init__.py
pyprediktormapclient/model_index.py
pyprediktormapclient/opc_ua.py
pyprediktormapclient/shared.py
pyPrediktorMapClient-0.8.0.dist-info/LICENSE.txt
pyPrediktorMapClient-0.8.0.dist-info/METADATA
pyPrediktorMapClient-0.8.0.dist-info/WHEEL
pyPrediktorMapClient-0.8.0.dist-info/top_level.txt
pyPrediktorMapClient-0.8.0.dist-info/RECORD
